sm_widgets/__init__.py
sm_widgets/models/__init__.py
sm_widgets/models/entity.py
sm_widgets/models/ontology.py
sm_widgets/models/table.py
sm_widgets/prelude.py
sm_widgets/services/__init__.py
sm_widgets/services/search.py
sm_widgets/widgets/__init__.py
sm_widgets/widgets/annotator/__init__.py
sm_widgets/widgets/annotator/annotator.py
sm_widgets/widgets/annotator/assistant.py
sm_widgets/widgets/annotator/session.py
sm_widgets/widgets/annotator/tree_ordering.py
sm_widgets/widgets/base.py
sm_widgets/widgets/foldable_list.py
sm_widgets/widgets/jscodes/annotator.js.gz
sm_widgets/widgets/jscodes/foldable_list.js.gz
sm_widgets/widgets/jscodes/slider.js.gz
sm_widgets/widgets/slider.py
sm_widgets/widgets/sm_visualizer.py
sm_widgets_integration/__init__.py
sm_widgets_integration/common.py
sm_widgets_integration/wikidata.py
sm_widgets_integration/with_grams.py
sm_widgets-0.1.13.dist-info/LICENSE
sm_widgets-0.1.13.dist-info/WHEEL
sm_widgets-0.1.13.dist-info/METADATA
sm_widgets-0.1.13.dist-info/RECORD
