Metadata-Version: 2.1
Name: sm-widgets
Version: 0.1.13
Summary: 
License: MIT
Author: Binh Vu
Author-email: binh@toan2.com
Requires-Python: >=3.8,<4.0
Classifier: License :: OSI Approved :: MIT License
Classifier: Programming Language :: Python :: 3
Classifier: Programming Language :: Python :: 3.8
Classifier: Programming Language :: Python :: 3.9
Provides-Extra: integration
Requires-Dist: elasticsearch (>=7.12.1,<8.0.0)
Requires-Dist: fuzzywuzzy (>=0.18.0,<0.19.0)
Requires-Dist: ipycallback (>=0.2.5,<0.3.0)
Requires-Dist: kgdata (>=1.2.3,<2.0.0)
Requires-Dist: loguru (>=0.5.3,<0.6.0)
Requires-Dist: orjson (>=3.5.2,<4.0.0)
Requires-Dist: python-slugify (>=5.0.2,<6.0.0)
Requires-Dist: requests (>=2.25.1,<3.0.0)
Requires-Dist: sem-desc (>=0.1.14,<0.2.0)
Requires-Dist: tqdm (>=4.60.0,<5.0.0)
